pipenv_uv_migrate/__init__.py
pipenv_uv_migrate/__main__.py
pipenv_uv_migrate/loader.py
pipenv_uv_migrate/migration.py
pipenv_uv_migrate-0.3.0.dist-info/METADATA
pipenv_uv_migrate-0.3.0.dist-info/WHEEL
pipenv_uv_migrate-0.3.0.dist-info/entry_points.txt
pipenv_uv_migrate-0.3.0.dist-info/licenses/LICENSE
pipenv_uv_migrate-0.3.0.dist-info/RECORD
