Metadata-Version: 2.4
Name: pipenv-uv-migrate
Version: 0.3.0
Summary: This is simple migration script, migrate pipenv to uv
Project-URL: Homepage, https://github.com/yhino/pipenv-uv-migrate
Project-URL: Repository, https://github.com/yhino/pipenv-uv-migrate
Author-email: Yoshiyuki HINO <yhinoz@gmail.com>
License:                                  Apache License
License-File: LICENSE
Classifier: License :: OSI Approved :: Apache Software License
Classifier: Programming Language :: Python :: 3
Classifier: Programming Language :: Python :: 3.10
Classifier: Programming Language :: Python :: 3.11
Classifier: Programming Language :: Python :: 3.12
Classifier: Programming Language :: Python :: 3.13
Classifier: Topic :: Utilities
Requires-Python: >=3.10
Requires-Dist: packaging>=24.2
Requires-Dist: tomlkit>=0.13.2
Requires-Dist: typer>=0.14.0
